{
    "Activity": {
        "lying": 0,
        "sitting": 1,
        "standing": 2,
        "walking": 3,
        "running": 4,
        "cycling": 5,
        "nordic walking": 6,
        "watching tv": 7,
        "computer work": 8,
        "car driving": 9,
        "ascending stairs": 10,
        "descending stairs": 11,
        "vacuum cleaning": 12,
        "ironing": 13,
        "folding laundry": 14,
        "house cleaning": 15,
        "playing soccer": 16,
        "rope jumping": 17
    },
    "Attribute": {
        "motion": 0,
        "static": 1,
        "cyclic motion": 2,
        "intense motion": 3,
        "translation motion": 4,
        "free motion": 5,
        "body vertical": 6,
        "body incline": 7,
        "body horizontal": 8,
        "body forward": 9,
        "body backward": 10,
        "body up": 11,
        "body down": 12,
        "body in place": 13,
        "torso transform": 14,
        "arms motion": 15,
        "arms static": 16,
        "arms bent": 17,
        "arms straight": 18,
        "arms bent-straight transform": 19,
        "hands hold something": 20,
        "legs motion": 21,
        "legs static": 22,
        "legs bent": 23,
        "legs straight": 24,
        "legs bent-straight transform": 25,
        "legs alternate move forward": 26,
        "legs move up and/or down": 27,
        "seat": 28,
        "bike": 29,
        "poles": 30,
        "television": 31,
        "computer": 32,
        "car": 33,
        "stairs": 34,
        "vacuum": 35,
        "iron": 36,
        "clothes": 37,
        "soccer": 38,
        "rope": 39,
        "indoor": 40,
        "outdoor": 41
    },
    "Mark": {
        "0": [
            0,
            1,
            0,
            0,
            0,
            0,
            0,
            0,
            1,
            0,
            0,
            0,
            0,
            1,
            0,
            1,
            1,
            1,
            1,
            1,
            0,
            1,
            1,
            1,
            1,
            1,
            0,
            0,
            0,
            0,
            0,
            0,
            0,
            0,
            0,
            0,
            0,
            0,
            0,
            0,
            1,
            1
        ],
        "1": [
            0,
            1,
            0,
            0,
            0,
            0,
            1,
            0,
            0,
            0,
            0,
            0,
            0,
            1,
            0,
            1,
            1,
            1,
            1,
            1,
            0,
            0,
            1,
            1,
            0,
            0,
            0,
            0,
            1,
            0,
            0,
            0,
            0,
            0,
            0,
            0,
            0,
            0,
            0,
            0,
            1,
            1
        ],
        "2": [
            0,
            1,
            0,
            0,
            0,
            0,
            1,
            0,
            0,
            0,
            0,
            0,
            0,
            1,
            0,
            1,
            1,
            1,
            1,
            1,
            0,
            0,
            1,
            0,
            1,
            0,
            0,
            0,
            0,
            0,
            0,
            0,
            0,
            0,
            0,
            0,
            0,
            0,
            0,
            0,
            1,
            1
        ],
        "3": [
            1,
            0,
            1,
            0,
            1,
            0,
            1,
            0,
            0,
            1,
            0,
            0,
            0,
            0,
            0,
            1,
            0,
            0,
            0,
            1,
            0,
            1,
            0,
            0,
            0,
            1,
            1,
            0,
            0,
            0,
            0,
            0,
            0,
            0,
            0,
            0,
            0,
            0,
            0,
            0,
            1,
            1
        ],
        "4": [
            1,
            0,
            1,
            1,
            1,
            0,
            1,
            0,
            0,
            1,
            0,
            0,
            0,
            0,
            0,
            1,
            0,
            1,
            0,
            0,
            0,
            1,
            0,
            0,
            0,
            1,
            1,
            0,
            0,
            0,
            0,
            0,
            0,
            0,
            0,
            0,
            0,
            0,
            0,
            0,
            0,
            1
        ],
        "5": [
            1,
            0,
            1,
            0,
            1,
            0,
            0,
            1,
            0,
            1,
            0,
            0,
            0,
            0,
            0,
            0,
            1,
            1,
            1,
            0,
            1,
            1,
            0,
            0,
            1,
            0,
            0,
            1,
            1,
            0,
            0,
            0,
            0,
            0,
            0,
            0,
            0,
            0,
            0,
            0,
            0,
            1
        ],
        "6": [
            1,
            0,
            1,
            0,
            1,
            0,
            1,
            0,
            0,
            1,
            0,
            0,
            0,
            0,
            0,
            1,
            0,
            0,
            0,
            1,
            1,
            1,
            0,
            0,
            0,
            1,
            1,
            0,
            0,
            0,
            1,
            0,
            0,
            0,
            0,
            0,
            0,
            0,
            0,
            0,
            0,
            1
        ],
        "7": [
            0,
            1,
            0,
            0,
            0,
            0,
            1,
            1,
            0,
            0,
            0,
            0,
            0,
            1,
            0,
            1,
            1,
            1,
            1,
            1,
            0,
            1,
            1,
            1,
            1,
            1,
            0,
            0,
            1,
            0,
            0,
            1,
            0,
            0,
            0,
            0,
            0,
            0,
            0,
            0,
            1,
            0
        ],
        "8": [
            0,
            1,
            0,
            0,
            0,
            0,
            1,
            1,
            0,
            0,
            0,
            0,
            0,
            1,
            0,
            1,
            1,
            1,
            1,
            1,
            1,
            1,
            1,
            1,
            0,
            0,
            0,
            0,
            1,
            0,
            0,
            0,
            1,
            0,
            0,
            0,
            0,
            0,
            0,
            0,
            1,
            0
        ],
        "9": [
            0,
            1,
            0,
            0,
            0,
            0,
            1,
            0,
            0,
            1,
            0,
            0,
            0,
            0,
            0,
            1,
            0,
            1,
            0,
            0,
            1,
            1,
            1,
            1,
            0,
            0,
            0,
            0,
            1,
            0,
            0,
            0,
            0,
            1,
            0,
            0,
            0,
            0,
            0,
            0,
            0,
            1
        ],
        "10": [
            1,
            0,
            1,
            0,
            0,
            0,
            1,
            1,
            0,
            1,
            0,
            1,
            0,
            0,
            0,
            1,
            0,
            1,
            1,
            1,
            1,
            1,
            0,
            0,
            0,
            1,
            1,
            1,
            0,
            0,
            0,
            0,
            0,
            0,
            1,
            0,
            0,
            0,
            0,
            0,
            1,
            1
        ],
        "11": [
            1,
            0,
            1,
            0,
            0,
            0,
            1,
            1,
            0,
            1,
            0,
            0,
            1,
            0,
            0,
            1,
            0,
            1,
            1,
            1,
            1,
            1,
            0,
            0,
            0,
            1,
            1,
            1,
            0,
            0,
            0,
            0,
            0,
            0,
            1,
            0,
            0,
            0,
            0,
            0,
            1,
            1
        ],
        "12": [
            1,
            0,
            0,
            0,
            0,
            1,
            1,
            1,
            0,
            1,
            1,
            0,
            0,
            0,
            1,
            1,
            0,
            1,
            1,
            1,
            1,
            1,
            0,
            1,
            1,
            1,
            0,
            0,
            0,
            0,
            0,
            0,
            0,
            0,
            0,
            1,
            0,
            0,
            0,
            0,
            1,
            0
        ],
        "13": [
            1,
            0,
            0,
            0,
            0,
            1,
            1,
            1,
            0,
            0,
            0,
            0,
            0,
            1,
            1,
            1,
            0,
            1,
            1,
            1,
            1,
            1,
            0,
            1,
            1,
            0,
            0,
            0,
            1,
            0,
            0,
            0,
            0,
            0,
            0,
            0,
            1,
            1,
            0,
            0,
            1,
            0
        ],
        "14": [
            1,
            0,
            0,
            0,
            0,
            1,
            1,
            1,
            0,
            0,
            0,
            0,
            0,
            1,
            1,
            1,
            0,
            1,
            1,
            1,
            1,
            1,
            1,
            1,
            1,
            1,
            0,
            0,
            1,
            0,
            0,
            0,
            0,
            0,
            0,
            0,
            0,
            1,
            0,
            0,
            1,
            0
        ],
        "15": [
            1,
            0,
            0,
            0,
            0,
            1,
            1,
            1,
            0,
            1,
            1,
            1,
            1,
            1,
            1,
            1,
            0,
            1,
            1,
            1,
            1,
            1,
            0,
            1,
            1,
            1,
            0,
            1,
            1,
            0,
            0,
            0,
            0,
            0,
            0,
            1,
            0,
            0,
            0,
            0,
            1,
            0
        ],
        "16": [
            1,
            0,
            0,
            1,
            0,
            1,
            1,
            1,
            0,
            1,
            0,
            1,
            1,
            0,
            1,
            1,
            0,
            1,
            1,
            1,
            0,
            1,
            0,
            1,
            1,
            1,
            1,
            0,
            0,
            0,
            0,
            0,
            0,
            0,
            0,
            0,
            0,
            0,
            1,
            0,
            0,
            1
        ],
        "17": [
            1,
            0,
            1,
            1,
            0,
            0,
            1,
            0,
            0,
            0,
            0,
            1,
            1,
            1,
            0,
            1,
            0,
            1,
            1,
            1,
            1,
            1,
            0,
            1,
            1,
            1,
            0,
            1,
            0,
            0,
            0,
            0,
            0,
            0,
            0,
            0,
            0,
            0,
            0,
            1,
            0,
            1
        ]
    }
}